README.md
setup.py
akiwi/__init__.py
akiwi/__main__.py
akiwi/app.py
akiwi/check.py
akiwi/http.py
akiwi/utils.py
akiwi/version.py
akiwi.egg-info/PKG-INFO
akiwi.egg-info/SOURCES.txt
akiwi.egg-info/dependency_links.txt
akiwi.egg-info/entry_points.txt
akiwi.egg-info/not-zip-safe
akiwi.egg-info/requires.txt
akiwi.egg-info/top_level.txt
akiwi/bin/kiwi.sh-temp